LICENSE
MANIFEST.in
README.rst
setup.cfg
setup.py
django_rest_framework_datatables_filter/__init__.py
django_rest_framework_datatables_filter/filters.py
django_rest_framework_datatables_filter/pagination.py
django_rest_framework_datatables_filter/renderers.py
django_rest_framework_datatables_filter/utils.py
django_rest_framework_datatables_filter.egg-info/PKG-INFO
django_rest_framework_datatables_filter.egg-info/SOURCES.txt
django_rest_framework_datatables_filter.egg-info/dependency_links.txt
django_rest_framework_datatables_filter.egg-info/requires.txt
django_rest_framework_datatables_filter.egg-info/top_level.txt
django_rest_framework_datatables_filter/django_filters/__init__.py
django_rest_framework_datatables_filter/django_filters/backends.py
django_rest_framework_datatables_filter/django_filters/filters.py
django_rest_framework_datatables_filter/django_filters/filterset.py